<?xml version="1.0" encoding="UTF-8" ?>
<!DOCTYPE mapper PUBLIC "-//mybatis.org//DTD Mapper 3.0//EN" "http://mybatis.org/dtd/mybatis-3-mapper.dtd">
<!-- Mybatis mapper for BlogDescription  Auto generated by fms-mybatis-generator -->
<mapper namespace="com.arc.zero.mapper.blog.BlogDescriptionMapper">
    <resultMap id="blogDescription" type="com.arc.core.model.domain.blog.BlogDescription">
        <id property="id" column="blog_description_id" javaType="long" jdbcType="BIGINT" />
        <result property="articleId" column="blog_description_article_id" javaType="long" jdbcType="BIGINT" />
        <result property="title" column="blog_description_title" javaType="string" jdbcType="VARCHAR" />
        <result property="description" column="blog_description_description" javaType="string" jdbcType="VARCHAR" />
        <result property="word" column="blog_description_word" javaType="int" jdbcType="INTEGER" />
        <result property="keyword" column="blog_description_keyword" javaType="string" jdbcType="VARCHAR" />
        <result property="prefer" column="blog_description_prefer" javaType="int" jdbcType="INTEGER" />
        <result property="clickCount" column="blog_description_click_count" javaType="int" jdbcType="INTEGER" />
        <result property="authorId" column="blog_description_author_id" javaType="long" jdbcType="BIGINT" />
        <result property="status" column="blog_description_status" javaType="int" jdbcType="INTEGER" />
        <result property="updateDate" column="blog_description_update_date" javaType="java.util.Date" jdbcType="TIMESTAMP" />
    </resultMap>

    <sql id="sqlBlogDescriptionColumns">
		blog_description_.id AS blog_description_id,
		blog_description_.article_id AS blog_description_article_id,
		blog_description_.title AS blog_description_title,
		blog_description_.description AS blog_description_description,
		blog_description_.word AS blog_description_word,
		blog_description_.keyword AS blog_description_keyword,
		blog_description_.prefer AS blog_description_prefer,
		blog_description_.click_count AS blog_description_click_count,
		blog_description_.author_id AS blog_description_author_id,
		blog_description_.status AS blog_description_status,
		blog_description_.update_date AS blog_description_update_date
	</sql>

    <delete id="delete" parameterType="long"  >
        DELETE FROM  t_blog_description
        WHERE  id = #{id,jdbcType=BIGINT}
    </delete>

    <select id="get" parameterType="long" resultMap="blogDescription">
        SELECT <include refid="sqlBlogDescriptionColumns" />
        FROM t_blog_description blog_description_
        WHERE blog_description_.id = #{id,jdbcType=BIGINT}
    </select>

    <select id="list"  resultMap="blogDescription">
        SELECT <include refid="sqlBlogDescriptionColumns" />
        FROM t_blog_description blog_description_
    </select>


    <insert id="save" parameterType="com.arc.core.model.domain.blog.BlogDescription" useGeneratedKeys="true" keyProperty="id">
		INSERT INTO t_blog_description (
			article_id,
			title,
			description,
			word,
			keyword,
			prefer,
			click_count,
			author_id,
			status,
			update_date
		)
        VALUES (
			#{articleId,jdbcType=BIGINT},
			#{title,jdbcType=VARCHAR},
			#{description,jdbcType=VARCHAR},
			#{word,jdbcType=INTEGER},
			#{keyword,jdbcType=VARCHAR},
			#{prefer,jdbcType=INTEGER},
			#{clickCount,jdbcType=INTEGER},
			#{authorId,jdbcType=BIGINT},
			#{status,jdbcType=INTEGER},
			#{updateDate,jdbcType=TIMESTAMP}
		)
	</insert>

    <update id="update" parameterType="com.arc.core.model.domain.blog.BlogDescription">
        UPDATE t_blog_description
        <set>
            <if test="articleId != null">article_id = #{articleId,jdbcType=BIGINT},</if>
            <if test="title != null and title != ''">title = #{title,jdbcType=VARCHAR},</if>
            <if test="description != null and description != ''">description = #{description,jdbcType=VARCHAR},</if>
            <if test="word != null">word = #{word,jdbcType=INTEGER},</if>
            <if test="keyword != null and keyword != ''">keyword = #{keyword,jdbcType=VARCHAR},</if>
            <if test="prefer != null">prefer = #{prefer,jdbcType=INTEGER},</if>
            <if test="clickCount != null">click_count = #{clickCount,jdbcType=INTEGER},</if>
            <if test="authorId != null">author_id = #{authorId,jdbcType=BIGINT},</if>
            <if test="status != null">status = #{status,jdbcType=INTEGER},</if>
            <if test="updateDate != null">update_date = #{updateDate,jdbcType=TIMESTAMP},</if>
        </set>
        WHERE id = #{id,jdbcType=BIGINT}
    </update>

</mapper>
